pypsse/__init__.py
pypsse/channel_map.py
pypsse/common.py
pypsse/compile.bat
pypsse/conec.flx
pypsse/conet.flx
pypsse/contingencies.py
pypsse/exceptions.py
pypsse/helics_interface.py
pypsse/mdao.py
pypsse/models.py
pypsse/pylogger.py
pypsse/pypsse_instance.py
pypsse/pypsse_logger.py
pypsse/pypsse_project.py
pypsse/result_container.py
pypsse/simulation_controller.py
pypsse/api/PSSE.v2.json
pypsse/api/__init__.py
pypsse/api/config.yaml
pypsse/api/pypsse.py
pypsse/api/server.py
pypsse/api/app/__init__.py
pypsse/api/app/psse.py
pypsse/api/web/__init__.py
pypsse/api/web/handler.py
pypsse/cli/__init__.py
pypsse/cli/create_profiles.py
pypsse/cli/create_project.py
pypsse/cli/pypsse.py
pypsse/cli/reports.py
pypsse/cli/run.py
pypsse/cli/serve.py
pypsse/data_writers/__init__.py
pypsse/data_writers/csv.py
pypsse/data_writers/data_writer.py
pypsse/data_writers/hdf5.py
pypsse/data_writers/json.py
pypsse/defaults/__init__.py
pypsse/defaults/export_settings.toml
pypsse/defaults/simulation_settings.toml
pypsse/modes/__init__.py
pypsse/modes/abstract_mode.py
pypsse/modes/constants.py
pypsse/modes/dynamic.py
pypsse/modes/pcm.py
pypsse/modes/snap.py
pypsse/modes/static.py
pypsse/parsers/__init__.py
pypsse/parsers/gic_parser.py
pypsse/parsers/reader.py
pypsse/profile_manager/__init__.py
pypsse/profile_manager/common.py
pypsse/profile_manager/profile.py
pypsse/profile_manager/profile_store.py
pypsse/utils/__init__.py
pypsse/utils/dynamic_utils.py
pypsse/utils/dc2ac/__init__.py
pypsse/utils/dc2ac/dc_ac_algorithm.py
pypsse/utils/dc2ac/helper_functions.py
pssepy-1.0.1.dist-info/METADATA
pssepy-1.0.1.dist-info/WHEEL
pssepy-1.0.1.dist-info/entry_points.txt
pssepy-1.0.1.dist-info/RECORD
