Metadata-Version: 2.1
Name: pssepy
Version: 1.0.1
Summary: A high-level python interface for PSS/E
Project-URL: Homepage, http://www.github.com/nrel/pypsse
Author-email: Aadil Latif <Aadil.Latif@nrel.gov>
License-Expression: BSD-3-Clause
Classifier: Development Status :: 4 - Beta
Classifier: Environment :: Console
Classifier: Environment :: Web Environment
Classifier: Intended Audience :: Developers
Classifier: Intended Audience :: Science/Research
Classifier: License :: OSI Approved :: BSD License
Classifier: Operating System :: OS Independent
Classifier: Programming Language :: Python :: 3
Requires-Python: >=3.8
Requires-Dist: aiohttp
Requires-Dist: aiohttp-cors
Requires-Dist: aiohttp-swagger
Requires-Dist: aiohttp-swagger3
Requires-Dist: click
Requires-Dist: h5py
Requires-Dist: helics
Requires-Dist: networkx
Requires-Dist: numpy
Requires-Dist: pandas
Requires-Dist: pydantic~=2.4
Requires-Dist: pytest
Requires-Dist: pyyaml
Requires-Dist: requests
Requires-Dist: terminaltables
Requires-Dist: toml
Requires-Dist: xlrd
